[
  {
    "passWord": "pass123",
    "firstName": "John",
    "nationality": "American",
    "socialSecurityNumber": "123-45-6789",
    "name": "Doe",
    "secretCode": "abc123",
    "dateOfBirth": "1944-05-10"
  },
  {
    "passWord": "pass456",
    "firstName": "Jane",
    "nationality": "British",
    "socialSecurityNumber": "234-56-7890",
    "name": "Smith",
    "secretCode": "xyz456",
    "dateOfBirth": "1954-07-22"
  },
  {
    "passWord": "pass789",
    "firstName": "Jean",
    "nationality": "French",
    "socialSecurityNumber": "99",
    "name": "Dupont",
    "secretCode": "qwe789",
    "dateOfBirth": "1964-12-13"
  },
  {
    "passWord": "a",
    "firstName": "a",
    "nationality": "a",
    "socialSecurityNumber": "a",
    "name": "a",
    "secretCode": "ty",
    "dateOfBirth": "2024-04-29"
  },
  {
    "passWord": "efeee",
    "firstName": "ga",
    "nationality": "bv",
    "socialSecurityNumber": "'''",
    "name": "are",
    "secretCode": "ty",
    "dateOfBirth": "2024-05-09"
  },
  {
    "passWord": "test",
    "firstName": "test",
    "nationality": "test",
    "socialSecurityNumber": "test",
    "name": "test",
    "secretCode": "test",
    "dateOfBirth": "test"
  },
  {
    "passWord": "az",
    "firstName": "az",
    "nationality": "az",
    "socialSecurityNumber": "az",
    "name": "az",
    "secretCode": "890e4b21-aaa2-450d-8923-0627242bded8",
    "dateOfBirth": "2024-05-01"
  },
  {
    "passWord": "qq",
    "firstName": "qq",
    "nationality": "qq",
    "socialSecurityNumber": "qq",
    "name": "qq",
    "secretCode": "f2f55f5c-780d-4a44-babb-192b95d9190b",
    "dateOfBirth": "2024-05-01"
  },
  {
    "passWord": "aaaaa",
    "firstName": "aude",
    "nationality": "Française",
    "socialSecurityNumber": "aaaaaaaa",
    "name": "Souchon",
    "secretCode": "128eaf9e-181a-4d03-92a7-48024f2d976e",
    "dateOfBirth": "2024-05-14"
  },
  {
    "passWord": "aaaaaaaaaaa",
    "firstName": "eeee",
    "nationality": "fce",
    "socialSecurityNumber": "xz",
    "name": "v\"bté'crxedz",
    "secretCode": "08cb87b7-776f-4d9b-ba7a-2f9eb863d276",
    "dateOfBirth": "2020-05-06"
  },
  {
    "passWord": "tvr",
    "firstName": "r&é\"",
    "nationality": "rfd\"e",
    "socialSecurityNumber": "véar",
    "name": "crf&\"",
    "secretCode": "012086fa-ab86-405d-ae83-bf357b641798",
    "dateOfBirth": "2024-05-03"
  },
  {
    "passWord": "test1234",
    "firstName": "mathis",
    "nationality": "France",
    "socialSecurityNumber": "12345",
    "name": "contassot",
    "secretCode": "b8d98e4b-5616-4558-85e3-f7e17c94e861",
    "dateOfBirth": "2003-09-20"
  }
]
